LICENSE
MANIFEST.in
README.md
setup.py
NlpToolkit_WordToVec_Cy.egg-info/PKG-INFO
NlpToolkit_WordToVec_Cy.egg-info/SOURCES.txt
NlpToolkit_WordToVec_Cy.egg-info/dependency_links.txt
NlpToolkit_WordToVec_Cy.egg-info/requires.txt
NlpToolkit_WordToVec_Cy.egg-info/top_level.txt
WordToVec/Iteration.c
WordToVec/Iteration.pxd
WordToVec/Iteration.pyx
WordToVec/NeuralNetwork.c
WordToVec/NeuralNetwork.pxd
WordToVec/NeuralNetwork.pyx
WordToVec/SemanticDataSet.c
WordToVec/SemanticDataSet.pxd
WordToVec/SemanticDataSet.pyx
WordToVec/Vocabulary.c
WordToVec/Vocabulary.pxd
WordToVec/Vocabulary.pyx
WordToVec/VocabularyWord.c
WordToVec/VocabularyWord.pxd
WordToVec/VocabularyWord.pyx
WordToVec/WordPair.c
WordToVec/WordPair.pxd
WordToVec/WordPair.pyx
WordToVec/WordToVecParameter.c
WordToVec/WordToVecParameter.pxd
WordToVec/WordToVecParameter.pyx
WordToVec/__init__.c
WordToVec/__init__.py
nlptoolkit_wordtovec_cy.egg-info/PKG-INFO
nlptoolkit_wordtovec_cy.egg-info/SOURCES.txt
nlptoolkit_wordtovec_cy.egg-info/dependency_links.txt
nlptoolkit_wordtovec_cy.egg-info/requires.txt
nlptoolkit_wordtovec_cy.egg-info/top_level.txt