Metadata-Version: 2.4
Name: nlptoolkit-wordtovec-cy
Version: 1.0.6
Summary: Word2Vec Library
Home-page: https://github.com/StarlangSoftware/WordToVec-Cy
Author: olcay
Author-email: olcay.yildiz@ozyegin.edu.tr
License-File: LICENSE
Requires-Dist: NlpToolkit-Corpus-Cy
Dynamic: author
Dynamic: author-email
Dynamic: description
Dynamic: description-content-type
Dynamic: home-page
Dynamic: license-file
Dynamic: requires-dist
Dynamic: summary
